kelpie/__init__.py
kelpie/arg_parser.py
kelpie/breeder.py
kelpie/calculation_workflows.py
kelpie/dos.py
kelpie/files_and_folders.py
kelpie/grazer.py
kelpie/io.py
kelpie/structure.py
kelpie/vasp_calculation_data.py
kelpie/vasp_input_generator.py
kelpie/vasp_output_parser.py
kelpie/vasp_run_manager.py
kelpie/data/__init__.py
kelpie/data/standard_atomic_weights.json
kelpie/data/valence_electrons.json
kelpie/scheduler_settings/__init__.py
kelpie/scheduler_settings/cori_haswell.json
kelpie/scheduler_settings/cori_knl.json
kelpie/scheduler_settings/cori_shared.json
kelpie/scheduler_settings/quest.json
kelpie/scheduler_templates/__init__.py
kelpie/scheduler_templates/cori.q
kelpie/scheduler_templates/cori_shared.q
kelpie/scheduler_templates/quest.q
kelpie/utils/__init__.py
kelpie/utils/serialization.py
kelpie/vasp_settings/__init__.py
kelpie/vasp_settings/incar/__init__.py
kelpie/vasp_settings/incar/acc_std_relax.json
kelpie/vasp_settings/incar/hubbards.json
kelpie/vasp_settings/incar/incar_tags_dict.json
kelpie/vasp_settings/incar/relaxation.json
kelpie/vasp_settings/incar/sc_forces.json
kelpie/vasp_settings/incar/static.json
kelpie/vasp_settings/potcar/__init__.py
kelpie/vasp_settings/potcar/vasp_reco_potcars.json
kelpie-0.6.2.data/scripts/kelpie
kelpie-0.6.2.dist-info/DESCRIPTION.rst
kelpie-0.6.2.dist-info/METADATA
kelpie-0.6.2.dist-info/RECORD
kelpie-0.6.2.dist-info/WHEEL
kelpie-0.6.2.dist-info/metadata.json
kelpie-0.6.2.dist-info/top_level.txt
