Metadata-Version: 2.0
Name: kelpie
Version: 0.6.2
Summary: A lean Python module for cluster-side management of VASP runs
Home-page: https://gitlab.com/hegdevinayi/kelpie
Author: Vinay Hegde
Author-email: hegdevinayi@gmail.com
License: MIT
Keywords: VASP DFT supercomputer high-throughput
Platform: UNKNOWN
Classifier: Development Status :: 3 - Alpha
Classifier: Programming Language :: Python :: 2
Classifier: Programming Language :: Python :: 2.7
Classifier: Programming Language :: Python :: 3
Classifier: Programming Language :: Python :: 3.6
Requires-Dist: six
Requires-Dist: lxml
Requires-Dist: numpy
